purplship/__init__.py
purplship/api_client.py
purplship/configuration.py
purplship/exceptions.py
purplship/model_utils.py
purplship/rest.py
purplship/api/__init__.py
purplship/api/addresses_api.py
purplship/api/api_api.py
purplship/api/carriers_api.py
purplship/api/customs_api.py
purplship/api/parcels_api.py
purplship/api/pickups_api.py
purplship/api/proxy_api.py
purplship/api/shipments_api.py
purplship/api/trackers_api.py
purplship/api/webhooks_api.py
purplship/apis/__init__.py
purplship/model/__init__.py
purplship/model/address.py
purplship/model/address_data.py
purplship/model/address_list.py
purplship/model/address_validation.py
purplship/model/carrier_list.py
purplship/model/carrier_settings.py
purplship/model/charge.py
purplship/model/commodity.py
purplship/model/commodity_data.py
purplship/model/customs.py
purplship/model/customs_data.py
purplship/model/customs_list.py
purplship/model/duty.py
purplship/model/error_response.py
purplship/model/message.py
purplship/model/metadata.py
purplship/model/operation.py
purplship/model/operation_confirmation.py
purplship/model/operation_response.py
purplship/model/parcel.py
purplship/model/parcel_data.py
purplship/model/parcel_list.py
purplship/model/payment.py
purplship/model/pickup.py
purplship/model/pickup_cancel_data.py
purplship/model/pickup_cancel_request.py
purplship/model/pickup_data.py
purplship/model/pickup_list.py
purplship/model/pickup_request.py
purplship/model/pickup_response.py
purplship/model/pickup_update_data.py
purplship/model/pickup_update_request.py
purplship/model/rate.py
purplship/model/rate_request.py
purplship/model/rate_response.py
purplship/model/references.py
purplship/model/shipment.py
purplship/model/shipment_cancel_request.py
purplship/model/shipment_data.py
purplship/model/shipment_list.py
purplship/model/shipment_purchase_data.py
purplship/model/shipment_rate_data.py
purplship/model/shipping_request.py
purplship_python-2021.11.dist-info/METADATA
purplship_python-2021.11.dist-info/RECORD
purplship_python-2021.11.dist-info/WHEEL
purplship_python-2021.11.dist-info/top_level.txt
