Metadata-Version: 2.1
Name: purplship-python
Version: 2021.11
Summary: purplship Multi-carrier Shipping API Python client library
Home-page: https://github.com/purplship/purplship-python-client
Author-email: hello@purplship.com
License: UNKNOWN
Keywords: purplship,Multi-carrier API,Shipping API
Platform: UNKNOWN
Classifier: Programming Language :: Python :: 3
Classifier: License :: OSI Approved :: MIT License
Classifier: Operating System :: OS Independent
Requires-Python: >=3.6
Requires-Dist: urllib3 (>=1.25.3)
Requires-Dist: python-dateutil
